{
	"sources" : 
	[
		{
			"file" : "C:/MeshEditor/90_Libraries/VTK-8.2.0/src/IO/PLY/vtkPLY.cxx"
		},
		{
			"file" : "C:/MeshEditor/90_Libraries/VTK-8.2.0/src/IO/PLY/vtkPLYReader.cxx"
		},
		{
			"file" : "C:/MeshEditor/90_Libraries/VTK-8.2.0/src/IO/PLY/vtkPLYWriter.cxx"
		},
		{
			"file" : "C:/MeshEditor/90_Libraries/VTK-8.2.0/src/IO/PLY/vtkPLY.h"
		},
		{
			"file" : "C:/MeshEditor/90_Libraries/VTK-8.2.0/src/IO/PLY/vtkPLYReader.h"
		},
		{
			"file" : "C:/MeshEditor/90_Libraries/VTK-8.2.0/src/IO/PLY/vtkPLYWriter.h"
		},
		{
			"file" : "C:/MeshEditor/90_Libraries/VTK-8.2.0/build/IO/PLY/vtkIOPLYModule.h"
		}
	],
	"target" : 
	{
		"labels" : 
		[
			"vtkIOPLY"
		],
		"name" : "vtkIOPLY"
	}
}